tox_direct/__init__.py
tox_direct/hookimpls.py
tox_direct-0.4.dist-info/LICENSE
tox_direct-0.4.dist-info/METADATA
tox_direct-0.4.dist-info/WHEEL
tox_direct-0.4.dist-info/entry_points.txt
tox_direct-0.4.dist-info/top_level.txt
tox_direct-0.4.dist-info/RECORD
