Metadata-Version: 2.1
Name: tox-direct
Version: 0.4
Summary: plugin for tox - run everything directly (tox creates no virtual env)
Home-page: https://github.com/obestwalter/tox-direct
Author: Oliver Bestwalter
Maintainer: Oliver Bestwalter
Maintainer-email: oliver@bestwalter.de
License: MIT
Project-URL: Source, https://github.com/obestwalter/tox-direct
Project-URL: Tracker, https://github.com/obestwalter/tox-direct/issues
Keywords: testing automation
Platform: any
Classifier: Development Status :: 4 - Beta
Classifier: Framework :: tox
Classifier: Intended Audience :: Developers
Classifier: License :: OSI Approved :: MIT License
Classifier: Programming Language :: Python
Classifier: Programming Language :: Python :: 2
Classifier: Programming Language :: Python :: 2.7
Classifier: Programming Language :: Python :: 3
Classifier: Programming Language :: Python :: 3.4
Classifier: Programming Language :: Python :: 3.5
Classifier: Programming Language :: Python :: 3.6
Classifier: Programming Language :: Python :: 3.7
Classifier: Programming Language :: Python :: Implementation :: CPython
Classifier: Programming Language :: Python :: Implementation :: PyPy
Classifier: Topic :: Software Development :: Testing
Requires-Dist: tox (<4,>=3.12)
Requires-Dist: py
Requires-Dist: pathlib2
Provides-Extra: publish
Requires-Dist: twine ; extra == 'publish'
Provides-Extra: test
Requires-Dist: pytest ; extra == 'test'
